img2desmos/__init__.py
img2desmos/main.py
img2desmos-1.1.0.dist-info/METADATA
img2desmos-1.1.0.dist-info/WHEEL
img2desmos-1.1.0.dist-info/entry_points.txt
img2desmos-1.1.0.dist-info/RECORD
