Metadata-Version: 2.1
Name: img2desmos
Version: 1.1.0
Summary: CLI tool to convert images to the LaTeX bezier curves formulas
Author: Perchinka
Author-email: aleksei.v.lukin@gmail.com
Requires-Python: >=3.9
Classifier: Programming Language :: Python :: 3
Classifier: Programming Language :: Python :: 3.9
Classifier: Programming Language :: Python :: 3.10
Classifier: Programming Language :: Python :: 3.11
Classifier: Programming Language :: Python :: 3.12
Requires-Dist: opencv-python (>=4.9.0.80,<5.0.0.0)
Requires-Dist: pillow (>=10.3.0,<11.0.0)
Requires-Dist: potracer (>=0.0.4,<0.0.5)
Requires-Dist: pyperclip (>=1.8.2,<2.0.0)
Requires-Dist: svg.path (>=6.3,<7.0)
Requires-Dist: sympy (>=1.12,<2.0)
Requires-Dist: termcolor (>=2.4.0,<3.0.0)
Requires-Dist: typer (>=0.12.3,<0.13.0)
